meilisearch/__init__.py
meilisearch/_httprequests.py
meilisearch/_utils.py
meilisearch/client.py
meilisearch/config.py
meilisearch/errors.py
meilisearch/index.py
meilisearch/py.typed
meilisearch/task.py
meilisearch/version.py
meilisearch/models/__init__.py
meilisearch/models/document.py
meilisearch/models/index.py
meilisearch/models/key.py
meilisearch/models/task.py
meilisearch-0.33.0.dist-info/LICENSE
meilisearch-0.33.0.dist-info/METADATA
meilisearch-0.33.0.dist-info/WHEEL
meilisearch-0.33.0.dist-info/top_level.txt
meilisearch-0.33.0.dist-info/RECORD
