Metadata-Version: 2.1
Name: meilisearch
Version: 0.33.0
Summary: The python client for Meilisearch API.
Author-email: Clémentine <clementine@meilisearch.com>
License: MIT
Project-URL: Meilisearch_Documentation, https://www.meilisearch.com/docs
Project-URL: Documentation, https://meilisearch.github.io/meilisearch-python/
Project-URL: Homepage, https://github.com/meilisearch/meilisearch-python
Keywords: search,python,meilisearch
Classifier: Programming Language :: Python :: 3
Classifier: Programming Language :: Python :: 3.9
Classifier: Programming Language :: Python :: 3.10
Classifier: Programming Language :: Python :: 3.11
Classifier: Programming Language :: Python :: 3.12
Classifier: Programming Language :: Python :: 3.13
Classifier: License :: OSI Approved :: MIT License
Classifier: Operating System :: OS Independent
Requires-Python: >=3.9
License-File: LICENSE
Requires-Dist: requests
Requires-Dist: camel-converter[pydantic]
